<?xml version="1.0" encoding="UTF-8" ?>
<JavaBean xmlns="http://xmlns.oracle.com/adfm/beanmodel" version="11.1.1.62.29"
          id="DataDirectorListener" Package="oracle.dss.util"
          BeanClass="oracle.dss.util.DataDirectorListener" isJavaBased="true">
  <MethodAccessor IsCollection="false" Type="void" id="viewDataChanged"
                  ReturnNodeName="Return">
    <ParameterInfo id="p0" Type="oracle.dss.util.DataChangedEvent"
                   isStructured="true"/>
  </MethodAccessor>
  <MethodAccessor IsCollection="false" Type="void" id="viewDataAvailable"
                  ReturnNodeName="Return">
    <ParameterInfo id="p0" Type="oracle.dss.util.DataAvailableEvent"
                   isStructured="true"/>
  </MethodAccessor>
  <MethodAccessor IsCollection="false" Type="void" id="waitDataAvailable"
                  ReturnNodeName="Return">
    <ParameterInfo id="p0" Type="oracle.dss.util.WaitDataAvailableEvent"
                   isStructured="true"/>
  </MethodAccessor>
  <MethodAccessor IsCollection="false" Type="void" id="pollingRequired"
                  ReturnNodeName="Return">
    <ParameterInfo id="p0" Type="oracle.dss.util.PollingRequiredEvent"
                   isStructured="true"/>
  </MethodAccessor>
</JavaBean>
